<?xml version="1.0" encoding="utf-8" ?>
<dwsync>
<file name="Benchmark.php" server="172.29.11.82//" local="130125492000000000" remote="130125492000000000" />
<file name="CodeIgniter.php" server="172.29.11.82//" local="130126356000000000" remote="130126356000000000" />
<file name="Common.php" server="172.29.11.82//" local="130125492000000000" remote="130125492000000000" />
<file name="Config.php" server="172.29.11.82//" local="130125492000000000" remote="130125492000000000" />
<file name="Controller.php" server="172.29.11.82//" local="130125492000000000" remote="130125492000000000" />
<file name="Exceptions.php" server="172.29.11.82//" local="130125492000000000" remote="130125492000000000" />
<file name="Hooks.php" server="172.29.11.82//" local="130125492000000000" remote="130125492000000000" />
<file name="Input.php" server="172.29.11.82//" local="130125492000000000" remote="130125492000000000" />
<file name="Lang.php" server="172.29.11.82//" local="130125492000000000" remote="130125492000000000" />
<file name="Loader.php" server="172.29.11.82//" local="130125492000000000" remote="130125492000000000" />
<file name="Model.php" server="172.29.11.82//" local="130125492000000000" remote="130125492000000000" />
<file name="Output.php" server="172.29.11.82//" local="130125492000000000" remote="130125492000000000" />
<file name="Router.php" server="172.29.11.82//" local="130125492000000000" remote="130125492000000000" />
<file name="Security.php" server="172.29.11.82//" local="130125492000000000" remote="130125492000000000" />
<file name="URI.php" server="172.29.11.82//" local="130125492000000000" remote="130125492000000000" />
<file name="Utf8.php" server="172.29.11.82//" local="130125492000000000" remote="130125492000000000" />
<file name="index.html" server="172.29.11.82//" local="130125492000000000" remote="130125492000000000" />
</dwsync>